[
    {
        "asin":  "B0755631862",
        "title":  "Gaming Chair Ergonomic Pro 3",
        "slug":  "gaming-chair-ergonomic-pro-200",
        "category":  "gaming",
        "rating":  4.8,
        "price":  106,
        "reviews":  49636,
        "affiliate_link":  "https://www.amazon.com/dp/B0755631862?tag=vh0805-20",
        "image":  "https://images.unsplash.com/photo-1606144042614-b2417e99c4e3?w=800",
        "date":  "2026-02-27"
    },
    {
        "asin":  "B0334578080",
        "title":  "Coffee Maker Programmable 3",
        "slug":  "coffee-maker-programmable-201",
        "category":  "home",
        "rating":  4.9,
        "price":  107,
        "reviews":  49637,
        "affiliate_link":  "https://www.amazon.com/dp/B0334578080?tag=vh0805-20",
        "image":  "https://images.unsplash.com/photo-1556909114-fcd25c85cd64?w=800",
        "date":  "2026-02-27"
    },
    {
        "asin":  "B0959939784",
        "title":  "Adjustable Dumbbells 52.5lbs 3",
        "slug":  "adjustable-dumbbells-525lbs-202",
        "category":  "fitness",
        "rating":  4.9,
        "price":  108,
        "reviews":  49638,
        "affiliate_link":  "https://www.amazon.com/dp/B0959939784?tag=vh0805-20",
        "image":  "https://i.ebayimg.com/images/g/lG0AAOSw77JnVv78/s-l500.jpg",
        "date":  "2026-02-27"
    },
    {
        "asin":  "B0069817994",
        "title":  "Roku Streaming Stick 4K 3",
        "slug":  "roku-streaming-stick-4k-203",
        "category":  "streaming",
        "rating":  5,
        "price":  109,
        "reviews":  49639,
        "affiliate_link":  "https://www.amazon.com/dp/B0069817994?tag=vh0805-20",
        "image":  "https://images.unsplash.com/photo-1593359677879-a4bb92f829d1?w=800",
        "date":  "2026-02-27"
    },
    {
        "asin":  "B0221385401",
        "title":  "Echo Dot 5th Gen 3",
        "slug":  "echo-dot-5th-gen-204",
        "category":  "smart-home",
        "rating":  3.5,
        "price":  110,
        "reviews":  49640,
        "affiliate_link":  "https://www.amazon.com/dp/B0221385401?tag=vh0805-20",
        "image":  "https://images.unsplash.com/photo-1558089687-f282ffcbc126?w=800",
        "date":  "2026-02-27"
    },
    {
        "asin":  "B0616760490",
        "title":  "Tablet Fire HD 10 3",
        "slug":  "tablet-fire-hd-10-205",
        "category":  "kindle",
        "rating":  3.6,
        "price":  111,
        "reviews":  49641,
        "affiliate_link":  "https://www.amazon.com/dp/B0616760490?tag=vh0805-20",
        "image":  "https://images.unsplash.com/photo-1544716278-ca5e3f4abd8c?w=800",
        "date":  "2026-02-27"
    },
    {
        "asin":  "B0659946547",
        "title":  "Smoker Box Pro Offset 3",
        "slug":  "smoker-box-pro-offset-206",
        "category":  "grills",
        "rating":  3.6,
        "price":  112,
        "reviews":  49642,
        "affiliate_link":  "https://www.amazon.com/dp/B0659946547?tag=vh0805-20",
        "image":  "https://images.unsplash.com/photo-1529193591184-b1d58069ecdd?w=800",
        "date":  "2026-02-27"
    },
    {
        "asin":  "B0382327686",
        "title":  "Rice Cooker Multi-Cook 3",
        "slug":  "rice-cooker-multi-cook-207",
        "category":  "kitchen",
        "rating":  3.7,
        "price":  113,
        "reviews":  49643,
        "affiliate_link":  "https://www.amazon.com/dp/B0382327686?tag=vh0805-20",
        "image":  "https://images.unsplash.com/photo-1556909114-f6e7ad7d3136?w=800",
        "date":  "2026-02-27"
    },
    {
        "asin":  "B0250857473",
        "title":  "USB-C Hub 7-in-1 3",
        "slug":  "usb-c-hub-7-in-1-208",
        "category":  "electronics",
        "rating":  3.7,
        "price":  114,
        "reviews":  49644,
        "affiliate_link":  "https://www.amazon.com/dp/B0250857473?tag=vh0805-20",
        "image":  "https://images.unsplash.com/photo-1498049794561-7780e7231661?w=800",
        "date":  "2026-02-27"
    },
    {
        "asin":  "B0573194796",
        "title":  "Gaming Headset 7.1 Surround 3",
        "slug":  "gaming-headset-71-surround-209",
        "category":  "audio",
        "rating":  3.8,
        "price":  115,
        "reviews":  49645,
        "affiliate_link":  "https://www.amazon.com/dp/B0573194796?tag=vh0805-20",
        "image":  "https://images.unsplash.com/photo-1505740420928-5e560c06d30e?w=800",
        "date":  "2026-02-27"
    },
    {
        "asin":  "B0166699768",
        "title":  "Hybrid Smart Watch Classic 3",
        "slug":  "hybrid-smart-watch-classic-210",
        "category":  "smartwatches",
        "rating":  4.9,
        "price":  137,
        "reviews":  49667,
        "affiliate_link":  "https://www.amazon.com/dp/B0166699768?tag=vh0805-20",
        "image":  "https://images.unsplash.com/photo-1523275335684-37898b6baf30?w=800",
        "date":  "2026-02-27"
    },
    {
        "asin":  "B0061905759",
        "title":  "4K Gaming Monitor 144Hz 3",
        "slug":  "4k-gaming-monitor-144hz-211",
        "category":  "gaming",
        "rating":  4.9,
        "price":  138,
        "reviews":  49668,
        "affiliate_link":  "https://www.amazon.com/dp/B0061905759?tag=vh0805-20",
        "image":  "https://images.unsplash.com/photo-1606144042614-b2417e99c4e3?w=800",
        "date":  "2026-02-27"
    },
    {
        "asin":  "B0282457555",
        "title":  "Instant Pot 7-in-1 3",
        "slug":  "instant-pot-7-in-1-212",
        "category":  "home",
        "rating":  5,
        "price":  139,
        "reviews":  49669,
        "affiliate_link":  "https://www.amazon.com/dp/B0282457555?tag=vh0805-20",
        "image":  "https://i.ebayimg.com/images/g/C8wAAeSwaJRpoFR3/s-l500.jpg",
        "date":  "2026-02-27"
    },
    {
        "asin":  "B0028824795",
        "title":  "Yoga Mat Premium 6mm 3",
        "slug":  "yoga-mat-premium-6mm-213",
        "category":  "fitness",
        "rating":  3.5,
        "price":  140,
        "reviews":  49670,
        "affiliate_link":  "https://www.amazon.com/dp/B0028824795?tag=vh0805-20",
        "image":  "https://images.unsplash.com/photo-1571019614242-c5c5dee9f50b?w=800",
        "date":  "2026-02-27"
    },
    {
        "asin":  "B0527258128",
        "title":  "Chromecast with Google TV 3",
        "slug":  "chromecast-with-google-tv-214",
        "category":  "streaming",
        "rating":  3.6,
        "price":  141,
        "reviews":  49671,
        "affiliate_link":  "https://www.amazon.com/dp/B0527258128?tag=vh0805-20",
        "image":  "https://images.unsplash.com/photo-1593359677879-a4bb92f829d1?w=800",
        "date":  "2026-02-27"
    },
    {
        "asin":  "B0194869566",
        "title":  "Smart Light Bulbs RGB 3",
        "slug":  "smart-light-bulbs-rgb-215",
        "category":  "smart-home",
        "rating":  3.6,
        "price":  142,
        "reviews":  49672,
        "affiliate_link":  "https://www.amazon.com/dp/B0194869566?tag=vh0805-20",
        "image":  "https://images.unsplash.com/photo-1558089687-f282ffcbc126?w=800",
        "date":  "2026-02-27"
    },
    {
        "asin":  "B0417674031",
        "title":  "E-Reader Kids Edition 3",
        "slug":  "e-reader-kids-edition-216",
        "category":  "kindle",
        "rating":  3.7,
        "price":  143,
        "reviews":  49673,
        "affiliate_link":  "https://www.amazon.com/dp/B0417674031?tag=vh0805-20",
        "image":  "https://images.unsplash.com/photo-1544716278-ca5e3f4abd8c?w=800",
        "date":  "2026-02-27"
    },
    {
        "asin":  "B0346831110",
        "title":  "Grill Accessories 20pc 3",
        "slug":  "grill-accessories-20pc-217",
        "category":  "grills",
        "rating":  3.7,
        "price":  144,
        "reviews":  49674,
        "affiliate_link":  "https://www.amazon.com/dp/B0346831110?tag=vh0805-20",
        "image":  "https://images.unsplash.com/photo-1529193591184-b1d58069ecdd?w=800",
        "date":  "2026-02-27"
    },
    {
        "asin":  "B0608269440",
        "title":  "Toaster Oven Digital 3",
        "slug":  "toaster-oven-digital-218",
        "category":  "kitchen",
        "rating":  3.8,
        "price":  145,
        "reviews":  49675,
        "affiliate_link":  "https://www.amazon.com/dp/B0608269440?tag=vh0805-20",
        "image":  "https://images.unsplash.com/photo-1556909114-f6e7ad7d3136?w=800",
        "date":  "2026-02-27"
    },
    {
        "asin":  "B0339487007",
        "title":  "Webcam 4K Pro 3",
        "slug":  "webcam-4k-pro-219",
        "category":  "electronics",
        "rating":  3.8,
        "price":  146,
        "reviews":  49676,
        "affiliate_link":  "https://www.amazon.com/dp/B0339487007?tag=vh0805-20",
        "image":  "https://images.unsplash.com/photo-1498049794561-7780e7231661?w=800",
        "date":  "2026-02-27"
    },
    {
        "asin":  "B0654804238",
        "title":  "Studio Monitor Speakers 3",
        "slug":  "studio-monitor-speakers-220",
        "category":  "audio",
        "rating":  4.9,
        "price":  168,
        "reviews":  49698,
        "affiliate_link":  "https://www.amazon.com/dp/B0654804238?tag=vh0805-20",
        "image":  "https://images.unsplash.com/photo-1505740420928-5e560c06d30e?w=800",
        "date":  "2026-02-27"
    },
    {
        "asin":  "B0082773616",
        "title":  "Sports Watch Pro AMOLED 3",
        "slug":  "sports-watch-pro-amoled-221",
        "category":  "smartwatches",
        "rating":  5,
        "price":  169,
        "reviews":  49699,
        "affiliate_link":  "https://www.amazon.com/dp/B0082773616?tag=vh0805-20",
        "image":  "https://images.unsplash.com/photo-1523275335684-37898b6baf30?w=800",
        "date":  "2026-02-27"
    },
    {
        "asin":  "B0196859042",
        "title":  "Console Controller Pro 3",
        "slug":  "console-controller-pro-222",
        "category":  "gaming",
        "rating":  3.5,
        "price":  170,
        "reviews":  49700,
        "affiliate_link":  "https://www.amazon.com/dp/B0196859042?tag=vh0805-20",
        "image":  "https://images.unsplash.com/photo-1606144042614-b2417e99c4e3?w=800",
        "date":  "2026-02-27"
    },
    {
        "asin":  "B0877357781",
        "title":  "Blender Professional 1200W 3",
        "slug":  "blender-professional-1200w-223",
        "category":  "home",
        "rating":  3.6,
        "price":  171,
        "reviews":  49701,
        "affiliate_link":  "https://www.amazon.com/dp/B0877357781?tag=vh0805-20",
        "image":  "https://i.ebayimg.com/images/g/nJkAAeSwjnRoxpZ7/s-l500.jpg",
        "date":  "2026-02-27"
    },
    {
        "asin":  "B0302533141",
        "title":  "Foam Roller Recovery 3",
        "slug":  "foam-roller-recovery-224",
        "category":  "fitness",
        "rating":  3.6,
        "price":  172,
        "reviews":  49702,
        "affiliate_link":  "https://www.amazon.com/dp/B0302533141?tag=vh0805-20",
        "image":  "https://images.unsplash.com/photo-1571019614242-c5c5dee9f50b?w=800",
        "date":  "2026-02-27"
    },
    {
        "asin":  "B0054595715",
        "title":  "Android TV Box 8K 3",
        "slug":  "android-tv-box-8k-225",
        "category":  "streaming",
        "rating":  3.7,
        "price":  173,
        "reviews":  49703,
        "affiliate_link":  "https://www.amazon.com/dp/B0054595715?tag=vh0805-20",
        "image":  "https://images.unsplash.com/photo-1593359677879-a4bb92f829d1?w=800",
        "date":  "2026-02-27"
    },
    {
        "asin":  "B0454283728",
        "title":  "Motion Sensor Kit 3",
        "slug":  "motion-sensor-kit-226",
        "category":  "smart-home",
        "rating":  3.7,
        "price":  174,
        "reviews":  49704,
        "affiliate_link":  "https://www.amazon.com/dp/B0454283728?tag=vh0805-20",
        "image":  "https://images.unsplash.com/photo-1558089687-f282ffcbc126?w=800",
        "date":  "2026-02-27"
    },
    {
        "asin":  "B0303310970",
        "title":  "Tablet 8\" HD Kids 3",
        "slug":  "tablet-8-hd-kids-227",
        "category":  "kindle",
        "rating":  3.8,
        "price":  175,
        "reviews":  49705,
        "affiliate_link":  "https://www.amazon.com/dp/B0303310970?tag=vh0805-20",
        "image":  "https://images.unsplash.com/photo-1544716278-ca5e3f4abd8c?w=800",
        "date":  "2026-02-27"
    },
    {
        "asin":  "B0822525489",
        "title":  "BBQ Tool Set Deluxe 3",
        "slug":  "bbq-tool-set-deluxe-228",
        "category":  "grills",
        "rating":  3.8,
        "price":  176,
        "reviews":  49706,
        "affiliate_link":  "https://www.amazon.com/dp/B0822525489?tag=vh0805-20",
        "image":  "https://images.unsplash.com/photo-1529193591184-b1d58069ecdd?w=800",
        "date":  "2026-02-27"
    },
    {
        "asin":  "B0230252292",
        "title":  "Hand Mixer Stand Mix 3",
        "slug":  "hand-mixer-stand-mix-229",
        "category":  "kitchen",
        "rating":  3.9,
        "price":  177,
        "reviews":  49707,
        "affiliate_link":  "https://www.amazon.com/dp/B0230252292?tag=vh0805-20",
        "image":  "https://images.unsplash.com/photo-1556909114-f6e7ad7d3136?w=800",
        "date":  "2026-02-27"
    },
    {
        "asin":  "B0958592886",
        "title":  "External SSD 2TB 3",
        "slug":  "external-ssd-2tb-230",
        "category":  "electronics",
        "rating":  5,
        "price":  199,
        "reviews":  49729,
        "affiliate_link":  "https://www.amazon.com/dp/B0958592886?tag=vh0805-20",
        "image":  "https://images.unsplash.com/photo-1498049794561-7780e7231661?w=800",
        "date":  "2026-02-27"
    },
    {
        "asin":  "B0460534358",
        "title":  "Neckband Wireless Earbuds 3",
        "slug":  "neckband-wireless-earbuds-231",
        "category":  "audio",
        "rating":  3.5,
        "price":  200,
        "reviews":  49730,
        "affiliate_link":  "https://www.amazon.com/dp/B0460534358?tag=vh0805-20",
        "image":  "https://images.unsplash.com/photo-1505740420928-5e560c06d30e?w=800",
        "date":  "2026-02-27"
    },
    {
        "asin":  "B0380910571",
        "title":  "Fashion Smart Watch 3",
        "slug":  "fashion-smart-watch-232",
        "category":  "smartwatches",
        "rating":  3.6,
        "price":  201,
        "reviews":  49731,
        "affiliate_link":  "https://www.amazon.com/dp/B0380910571?tag=vh0805-20",
        "image":  "https://images.unsplash.com/photo-1523275335684-37898b6baf30?w=800",
        "date":  "2026-02-27"
    },
    {
        "asin":  "B0804109801",
        "title":  "VR Headset System 3",
        "slug":  "vr-headset-system-233",
        "category":  "gaming",
        "rating":  3.6,
        "price":  202,
        "reviews":  49732,
        "affiliate_link":  "https://www.amazon.com/dp/B0804109801?tag=vh0805-20",
        "image":  "https://images.unsplash.com/photo-1606144042614-b2417e99c4e3?w=800",
        "date":  "2026-02-27"
    },
    {
        "asin":  "B0349920096",
        "title":  "Air Fryer XXL Digital 3",
        "slug":  "air-fryer-xxl-digital-234",
        "category":  "home",
        "rating":  3.7,
        "price":  203,
        "reviews":  49733,
        "affiliate_link":  "https://www.amazon.com/dp/B0349920096?tag=vh0805-20",
        "image":  "https://images.unsplash.com/photo-1556909114-fcd25c85cd64?w=800",
        "date":  "2026-02-27"
    },
    {
        "asin":  "B0120100995",
        "title":  "Pull Up Bar Doorway 3",
        "slug":  "pull-up-bar-doorway-235",
        "category":  "fitness",
        "rating":  3.7,
        "price":  204,
        "reviews":  49734,
        "affiliate_link":  "https://www.amazon.com/dp/B0120100995?tag=vh0805-20",
        "image":  "https://images.unsplash.com/photo-1571019614242-c5c5dee9f50b?w=800",
        "date":  "2026-02-27"
    },
    {
        "asin":  "B0854509849",
        "title":  "Apple TV 4K 3",
        "slug":  "apple-tv-4k-236",
        "category":  "streaming",
        "rating":  3.8,
        "price":  205,
        "reviews":  49735,
        "affiliate_link":  "https://www.amazon.com/dp/B0854509849?tag=vh0805-20",
        "image":  "https://images.unsplash.com/photo-1593359677879-a4bb92f829d1?w=800",
        "date":  "2026-02-27"
    },
    {
        "asin":  "B0206924917",
        "title":  "Smart Plug Mini 3",
        "slug":  "smart-plug-mini-237",
        "category":  "smart-home",
        "rating":  3.8,
        "price":  206,
        "reviews":  49736,
        "affiliate_link":  "https://www.amazon.com/dp/B0206924917?tag=vh0805-20",
        "image":  "https://images.unsplash.com/photo-1558089687-f282ffcbc126?w=800",
        "date":  "2026-02-27"
    },
    {
        "asin":  "B0267378870",
        "title":  "Reading Light Clip On 3",
        "slug":  "reading-light-clip-on-238",
        "category":  "kindle",
        "rating":  3.9,
        "price":  207,
        "reviews":  49737,
        "affiliate_link":  "https://www.amazon.com/dp/B0267378870?tag=vh0805-20",
        "image":  "https://images.unsplash.com/photo-1544716278-ca5e3f4abd8c?w=800",
        "date":  "2026-02-27"
    },
    {
        "asin":  "B0643657974",
        "title":  "Grill Cover Waterproof 3",
        "slug":  "grill-cover-waterproof-239",
        "category":  "grills",
        "rating":  3.9,
        "price":  208,
        "reviews":  49738,
        "affiliate_link":  "https://www.amazon.com/dp/B0643657974?tag=vh0805-20",
        "image":  "https://images.unsplash.com/photo-1529193591184-b1d58069ecdd?w=800",
        "date":  "2026-02-27"
    },
    {
        "asin":  "B0283949619",
        "title":  "Immersion Blender 800W 3",
        "slug":  "immersion-blender-800w-240",
        "category":  "kitchen",
        "rating":  3.5,
        "price":  230,
        "reviews":  49760,
        "affiliate_link":  "https://www.amazon.com/dp/B0283949619?tag=vh0805-20",
        "image":  "https://images.unsplash.com/photo-1556909114-f6e7ad7d3136?w=800",
        "date":  "2026-02-27"
    },
    {
        "asin":  "B0210253527",
        "title":  "Bluetooth 5.0 Adapter 3",
        "slug":  "bluetooth-50-adapter-241",
        "category":  "electronics",
        "rating":  3.6,
        "price":  231,
        "reviews":  49761,
        "affiliate_link":  "https://www.amazon.com/dp/B0210253527?tag=vh0805-20",
        "image":  "https://images.unsplash.com/photo-1498049794561-7780e7231661?w=800",
        "date":  "2026-02-27"
    },
    {
        "asin":  "B0010902930",
        "title":  "Waterproof Speaker IPX7 3",
        "slug":  "waterproof-speaker-ipx7-242",
        "category":  "audio",
        "rating":  3.6,
        "price":  232,
        "reviews":  49762,
        "affiliate_link":  "https://www.amazon.com/dp/B0010902930?tag=vh0805-20",
        "image":  "https://images.unsplash.com/photo-1505740420928-5e560c06d30e?w=800",
        "date":  "2026-02-27"
    },
    {
        "asin":  "B0366344143",
        "title":  "Diver Watch Smart 3",
        "slug":  "diver-watch-smart-243",
        "category":  "smartwatches",
        "rating":  3.7,
        "price":  233,
        "reviews":  49763,
        "affiliate_link":  "https://www.amazon.com/dp/B0366344143?tag=vh0805-20",
        "image":  "https://images.unsplash.com/photo-1523275335684-37898b6baf30?w=800",
        "date":  "2026-02-27"
    },
    {
        "asin":  "B0855749399",
        "title":  "Gaming Router WiFi 6E 3",
        "slug":  "gaming-router-wifi-6e-244",
        "category":  "gaming",
        "rating":  3.7,
        "price":  234,
        "reviews":  49764,
        "affiliate_link":  "https://www.amazon.com/dp/B0855749399?tag=vh0805-20",
        "image":  "https://images.unsplash.com/photo-1606144042614-b2417e99c4e3?w=800",
        "date":  "2026-02-27"
    },
    {
        "asin":  "B0967070466",
        "title":  "Robot Mop Automatic 3",
        "slug":  "robot-mop-automatic-245",
        "category":  "home",
        "rating":  3.8,
        "price":  235,
        "reviews":  49765,
        "affiliate_link":  "https://www.amazon.com/dp/B0967070466?tag=vh0805-20",
        "image":  "https://images.unsplash.com/photo-1556909114-fcd25c85cd64?w=800",
        "date":  "2026-02-27"
    },
    {
        "asin":  "B0056550036",
        "title":  "Kettlebell Set 5-25lbs 3",
        "slug":  "kettlebell-set-5-25lbs-246",
        "category":  "fitness",
        "rating":  3.8,
        "price":  236,
        "reviews":  49766,
        "affiliate_link":  "https://www.amazon.com/dp/B0056550036?tag=vh0805-20",
        "image":  "https://images.unsplash.com/photo-1571019614242-c5c5dee9f50b?w=800",
        "date":  "2026-02-27"
    },
    {
        "asin":  "B0474034628",
        "title":  "Nvidia Shield Pro 3",
        "slug":  "nvidia-shield-pro-247",
        "category":  "streaming",
        "rating":  3.9,
        "price":  237,
        "reviews":  49767,
        "affiliate_link":  "https://www.amazon.com/dp/B0474034628?tag=vh0805-20",
        "image":  "https://images.unsplash.com/photo-1593359677879-a4bb92f829d1?w=800",
        "date":  "2026-02-27"
    },
    {
        "asin":  "B0433247871",
        "title":  "Video Doorbell Pro 3",
        "slug":  "video-doorbell-pro-248",
        "category":  "smart-home",
        "rating":  3.9,
        "price":  238,
        "reviews":  49768,
        "affiliate_link":  "https://www.amazon.com/dp/B0433247871?tag=vh0805-20",
        "image":  "https://images.unsplash.com/photo-1558089687-f282ffcbc126?w=800",
        "date":  "2026-02-27"
    },
    {
        "asin":  "B0650533335",
        "title":  "Leather Cover Premium 3",
        "slug":  "leather-cover-premium-249",
        "category":  "kindle",
        "rating":  4,
        "price":  239,
        "reviews":  49769,
        "affiliate_link":  "https://www.amazon.com/dp/B0650533335?tag=vh0805-20",
        "image":  "https://images.unsplash.com/photo-1544716278-ca5e3f4abd8c?w=800",
        "date":  "2026-02-27"
    },
    {
        "asin":  "B0052987248",
        "title":  "Pellet Grill Smoker 3",
        "slug":  "pellet-grill-smoker-250",
        "category":  "grills",
        "rating":  3.6,
        "price":  261,
        "reviews":  49791,
        "affiliate_link":  "https://www.amazon.com/dp/B0052987248?tag=vh0805-20",
        "image":  "https://images.unsplash.com/photo-1529193591184-b1d58069ecdd?w=800",
        "date":  "2026-02-27"
    },
    {
        "asin":  "B0431537450",
        "title":  "Electric Kettle 1.7L 3",
        "slug":  "electric-kettle-17l-251",
        "category":  "kitchen",
        "rating":  3.6,
        "price":  262,
        "reviews":  49792,
        "affiliate_link":  "https://www.amazon.com/dp/B0431537450?tag=vh0805-20",
        "image":  "https://images.unsplash.com/photo-1556909114-f6e7ad7d3136?w=800",
        "date":  "2026-02-27"
    },
    {
        "asin":  "B0940965430",
        "title":  "Power Bank 30000mAh 3",
        "slug":  "power-bank-30000mah-252",
        "category":  "electronics",
        "rating":  3.7,
        "price":  263,
        "reviews":  49793,
        "affiliate_link":  "https://www.amazon.com/dp/B0940965430?tag=vh0805-20",
        "image":  "https://images.unsplash.com/photo-1498049794561-7780e7231661?w=800",
        "date":  "2026-02-27"
    },
    {
        "asin":  "B0739806819",
        "title":  "Over-Ear Headphones Premium 3",
        "slug":  "over-ear-headphones-premium-253",
        "category":  "audio",
        "rating":  3.7,
        "price":  264,
        "reviews":  49794,
        "affiliate_link":  "https://www.amazon.com/dp/B0739806819?tag=vh0805-20",
        "image":  "https://images.unsplash.com/photo-1505740420928-5e560c06d30e?w=800",
        "date":  "2026-02-27"
    },
    {
        "asin":  "B0291596989",
        "title":  "Classic Analog Smart Hybrid 3",
        "slug":  "classic-analog-smart-hybrid-254",
        "category":  "smartwatches",
        "rating":  3.8,
        "price":  265,
        "reviews":  49795,
        "affiliate_link":  "https://www.amazon.com/dp/B0291596989?tag=vh0805-20",
        "image":  "https://images.unsplash.com/photo-1523275335684-37898b6baf30?w=800",
        "date":  "2026-02-27"
    },
    {
        "asin":  "B0266713551",
        "title":  "Gaming Keyboard Mechanical 3",
        "slug":  "gaming-keyboard-mechanical-255",
        "category":  "gaming",
        "rating":  3.8,
        "price":  266,
        "reviews":  49796,
        "affiliate_link":  "https://www.amazon.com/dp/B0266713551?tag=vh0805-20",
        "image":  "https://images.unsplash.com/photo-1606144042614-b2417e99c4e3?w=800",
        "date":  "2026-02-27"
    },
    {
        "asin":  "B0494896485",
        "title":  "Dehumidifier Electric 3",
        "slug":  "dehumidifier-electric-256",
        "category":  "home",
        "rating":  3.9,
        "price":  267,
        "reviews":  49797,
        "affiliate_link":  "https://www.amazon.com/dp/B0494896485?tag=vh0805-20",
        "image":  "https://images.unsplash.com/photo-1556909114-fcd25c85cd64?w=800",
        "date":  "2026-02-27"
    },
    {
        "asin":  "B0919781359",
        "title":  "Rowing Machine Water 3",
        "slug":  "rowing-machine-water-257",
        "category":  "fitness",
        "rating":  3.9,
        "price":  268,
        "reviews":  49798,
        "affiliate_link":  "https://www.amazon.com/dp/B0919781359?tag=vh0805-20",
        "image":  "https://images.unsplash.com/photo-1571019614242-c5c5dee9f50b?w=800",
        "date":  "2026-02-27"
    },
    {
        "asin":  "B0139340162",
        "title":  "Amazon Fire TV Cube 3",
        "slug":  "amazon-fire-tv-cube-258",
        "category":  "streaming",
        "rating":  4,
        "price":  269,
        "reviews":  49799,
        "affiliate_link":  "https://www.amazon.com/dp/B0139340162?tag=vh0805-20",
        "image":  "https://images.unsplash.com/photo-1593359677879-a4bb92f829d1?w=800",
        "date":  "2026-02-27"
    },
    {
        "asin":  "B0054542954",
        "title":  "Garage Door Opener Smart 3",
        "slug":  "garage-door-opener-smart-259",
        "category":  "smart-home",
        "rating":  4,
        "price":  270,
        "reviews":  49800,
        "affiliate_link":  "https://www.amazon.com/dp/B0054542954?tag=vh0805-20",
        "image":  "https://images.unsplash.com/photo-1558089687-f282ffcbc126?w=800",
        "date":  "2026-02-27"
    },
    {
        "asin":  "B0888304912",
        "title":  "Tablet Stand Adjustable 3",
        "slug":  "tablet-stand-adjustable-260",
        "category":  "kindle",
        "rating":  3.6,
        "price":  292,
        "reviews":  49822,
        "affiliate_link":  "https://www.amazon.com/dp/B0888304912?tag=vh0805-20",
        "image":  "https://images.unsplash.com/photo-1544716278-ca5e3f4abd8c?w=800",
        "date":  "2026-02-27"
    },
    {
        "asin":  "B0326996897",
        "title":  "Propane Tank 20lb 3",
        "slug":  "propane-tank-20lb-261",
        "category":  "grills",
        "rating":  3.7,
        "price":  293,
        "reviews":  49823,
        "affiliate_link":  "https://www.amazon.com/dp/B0326996897?tag=vh0805-20",
        "image":  "https://images.unsplash.com/photo-1529193591184-b1d58069ecdd?w=800",
        "date":  "2026-02-27"
    },
    {
        "asin":  "B0131334713",
        "title":  "Sous Vide Precision 3",
        "slug":  "sous-vide-precision-262",
        "category":  "kitchen",
        "rating":  3.7,
        "price":  294,
        "reviews":  49824,
        "affiliate_link":  "https://www.amazon.com/dp/B0131334713?tag=vh0805-20",
        "image":  "https://images.unsplash.com/photo-1556909114-f6e7ad7d3136?w=800",
        "date":  "2026-02-27"
    },
    {
        "asin":  "B0584608531",
        "title":  "Smart Plug WiFi 4-pack 3",
        "slug":  "smart-plug-wifi-4-pack-263",
        "category":  "electronics",
        "rating":  3.8,
        "price":  295,
        "reviews":  49825,
        "affiliate_link":  "https://www.amazon.com/dp/B0584608531?tag=vh0805-20",
        "image":  "https://images.unsplash.com/photo-1498049794561-7780e7231661?w=800",
        "date":  "2026-02-27"
    },
    {
        "asin":  "B0779653989",
        "title":  "In-Ear Monitors HIFI 3",
        "slug":  "in-ear-monitors-hifi-264",
        "category":  "audio",
        "rating":  3.8,
        "price":  296,
        "reviews":  49826,
        "affiliate_link":  "https://www.amazon.com/dp/B0779653989?tag=vh0805-20",
        "image":  "https://images.unsplash.com/photo-1505740420928-5e560c06d30e?w=800",
        "date":  "2026-02-27"
    },
    {
        "asin":  "B0213614273",
        "title":  "GPS Running Watch 3",
        "slug":  "gps-running-watch-265",
        "category":  "smartwatches",
        "rating":  3.9,
        "price":  297,
        "reviews":  49827,
        "affiliate_link":  "https://www.amazon.com/dp/B0213614273?tag=vh0805-20",
        "image":  "https://images.unsplash.com/photo-1523275335684-37898b6baf30?w=800",
        "date":  "2026-02-27"
    },
    {
        "asin":  "B0685289453",
        "title":  "Racing Wheel Simulator 3",
        "slug":  "racing-wheel-simulator-266",
        "category":  "gaming",
        "rating":  3.9,
        "price":  298,
        "reviews":  49828,
        "affiliate_link":  "https://www.amazon.com/dp/B0685289453?tag=vh0805-20",
        "image":  "https://images.unsplash.com/photo-1606144042614-b2417e99c4e3?w=800",
        "date":  "2026-02-27"
    },
    {
        "asin":  "B0619388231",
        "title":  "Humidifier Ultrasonic 3",
        "slug":  "humidifier-ultrasonic-267",
        "category":  "home",
        "rating":  4,
        "price":  299,
        "reviews":  49829,
        "affiliate_link":  "https://www.amazon.com/dp/B0619388231?tag=vh0805-20",
        "image":  "https://images.unsplash.com/photo-1556909114-fcd25c85cd64?w=800",
        "date":  "2026-02-27"
    },
    {
        "asin":  "B0391258932",
        "title":  "Elliptical Trainer 3",
        "slug":  "elliptical-trainer-268",
        "category":  "fitness",
        "rating":  4,
        "price":  300,
        "reviews":  49830,
        "affiliate_link":  "https://www.amazon.com/dp/B0391258932?tag=vh0805-20",
        "image":  "https://images.unsplash.com/photo-1571019614242-c5c5dee9f50b?w=800",
        "date":  "2026-02-27"
    },
    {
        "asin":  "B0853531886",
        "title":  "TiVo Stream 4K 3",
        "slug":  "tivo-stream-4k-269",
        "category":  "streaming",
        "rating":  4.1,
        "price":  301,
        "reviews":  49831,
        "affiliate_link":  "https://www.amazon.com/dp/B0853531886?tag=vh0805-20",
        "image":  "https://images.unsplash.com/photo-1593359677879-a4bb92f829d1?w=800",
        "date":  "2026-02-27"
    },
    {
        "asin":  "B0460400536",
        "title":  "Smart Switch WiFi 3",
        "slug":  "smart-switch-wifi-270",
        "category":  "smart-home",
        "rating":  3.7,
        "price":  323,
        "reviews":  49853,
        "affiliate_link":  "https://www.amazon.com/dp/B0460400536?tag=vh0805-20",
        "image":  "https://images.unsplash.com/photo-1558089687-f282ffcbc126?w=800",
        "date":  "2026-02-27"
    },
    {
        "asin":  "B0048918943",
        "title":  "Stylus Pen Tablet 3",
        "slug":  "stylus-pen-tablet-271",
        "category":  "kindle",
        "rating":  3.7,
        "price":  324,
        "reviews":  49854,
        "affiliate_link":  "https://www.amazon.com/dp/B0048918943?tag=vh0805-20",
        "image":  "https://images.unsplash.com/photo-1544716278-ca5e3f4abd8c?w=800",
        "date":  "2026-02-27"
    },
    {
        "asin":  "B0006178989",
        "title":  "Charcoal chimney Starter 3",
        "slug":  "charcoal-chimney-starter-272",
        "category":  "grills",
        "rating":  3.8,
        "price":  325,
        "reviews":  49855,
        "affiliate_link":  "https://www.amazon.com/dp/B0006178989?tag=vh0805-20",
        "image":  "https://images.unsplash.com/photo-1529193591184-b1d58069ecdd?w=800",
        "date":  "2026-02-27"
    },
    {
        "asin":  "B0372739129",
        "title":  "Ice Cream Maker 3",
        "slug":  "ice-cream-maker-273",
        "category":  "kitchen",
        "rating":  3.8,
        "price":  326,
        "reviews":  49856,
        "affiliate_link":  "https://www.amazon.com/dp/B0372739129?tag=vh0805-20",
        "image":  "https://images.unsplash.com/photo-1556909114-f6e7ad7d3136?w=800",
        "date":  "2026-02-27"
    },
    {
        "asin":  "B0379475172",
        "title":  "LED Desk Lamp Eye Care 3",
        "slug":  "led-desk-lamp-eye-care-274",
        "category":  "electronics",
        "rating":  3.9,
        "price":  327,
        "reviews":  49857,
        "affiliate_link":  "https://www.amazon.com/dp/B0379475172?tag=vh0805-20",
        "image":  "https://images.unsplash.com/photo-1498049794561-7780e7231661?w=800",
        "date":  "2026-02-27"
    },
    {
        "asin":  "B0361080169",
        "title":  "Party Speaker LED Lights 3",
        "slug":  "party-speaker-led-lights-275",
        "category":  "audio",
        "rating":  3.9,
        "price":  328,
        "reviews":  49858,
        "affiliate_link":  "https://www.amazon.com/dp/B0361080169?tag=vh0805-20",
        "image":  "https://images.unsplash.com/photo-1505740420928-5e560c06d30e?w=800",
        "date":  "2026-02-27"
    },
    {
        "asin":  "B0432355125",
        "title":  "Triathlon Smart Watch 3",
        "slug":  "triathlon-smart-watch-276",
        "category":  "smartwatches",
        "rating":  4,
        "price":  329,
        "reviews":  49859,
        "affiliate_link":  "https://www.amazon.com/dp/B0432355125?tag=vh0805-20",
        "image":  "https://images.unsplash.com/photo-1523275335684-37898b6baf30?w=800",
        "date":  "2026-02-27"
    },
    {
        "asin":  "B0387414132",
        "title":  "Gaming Desk LED 3",
        "slug":  "gaming-desk-led-277",
        "category":  "gaming",
        "rating":  4,
        "price":  330,
        "reviews":  49860,
        "affiliate_link":  "https://www.amazon.com/dp/B0387414132?tag=vh0805-20",
        "image":  "https://images.unsplash.com/photo-1606144042614-b2417e99c4e3?w=800",
        "date":  "2026-02-27"
    },
    {
        "asin":  "B0142718857",
        "title":  "Vacuum Cleaner Bagless 3",
        "slug":  "vacuum-cleaner-bagless-278",
        "category":  "home",
        "rating":  4.1,
        "price":  331,
        "reviews":  49861,
        "affiliate_link":  "https://www.amazon.com/dp/B0142718857?tag=vh0805-20",
        "image":  "https://images.unsplash.com/photo-1556909114-fcd25c85cd64?w=800",
        "date":  "2026-02-27"
    },
    {
        "asin":  "B0391613346",
        "title":  "Weight Bench Adjustable 3",
        "slug":  "weight-bench-adjustable-279",
        "category":  "fitness",
        "rating":  4.1,
        "price":  332,
        "reviews":  49862,
        "affiliate_link":  "https://www.amazon.com/dp/B0391613346?tag=vh0805-20",
        "image":  "https://images.unsplash.com/photo-1571019614242-c5c5dee9f50b?w=800",
        "date":  "2026-02-27"
    },
    {
        "asin":  "B0789920439",
        "title":  "AT\u0026T TV Stream 3",
        "slug":  "att-tv-stream-280",
        "category":  "streaming",
        "rating":  3.7,
        "price":  354,
        "reviews":  49884,
        "affiliate_link":  "https://www.amazon.com/dp/B0789920439?tag=vh0805-20",
        "image":  "https://images.unsplash.com/photo-1593359677879-a4bb92f829d1?w=800",
        "date":  "2026-02-27"
    },
    {
        "asin":  "B0022688472",
        "title":  "Smart Thermostat Learning 3",
        "slug":  "smart-thermostat-learning-281",
        "category":  "smart-home",
        "rating":  3.8,
        "price":  355,
        "reviews":  49885,
        "affiliate_link":  "https://www.amazon.com/dp/B0022688472?tag=vh0805-20",
        "image":  "https://images.unsplash.com/photo-1558089687-f282ffcbc126?w=800",
        "date":  "2026-02-27"
    },
    {
        "asin":  "B0502608610",
        "title":  "Screen Protector Pack 3",
        "slug":  "screen-protector-pack-282",
        "category":  "kindle",
        "rating":  3.8,
        "price":  356,
        "reviews":  49886,
        "affiliate_link":  "https://www.amazon.com/dp/B0502608610?tag=vh0805-20",
        "image":  "https://images.unsplash.com/photo-1544716278-ca5e3f4abd8c?w=800",
        "date":  "2026-02-27"
    },
    {
        "asin":  "B0829785296",
        "title":  "Meat Thermometer Digital 3",
        "slug":  "meat-thermometer-digital-283",
        "category":  "grills",
        "rating":  3.9,
        "price":  357,
        "reviews":  49887,
        "affiliate_link":  "https://www.amazon.com/dp/B0829785296?tag=vh0805-20",
        "image":  "https://images.unsplash.com/photo-1529193591184-b1d58069ecdd?w=800",
        "date":  "2026-02-27"
    },
    {
        "asin":  "B0064380017",
        "title":  "Bread Maker Automatic 3",
        "slug":  "bread-maker-automatic-284",
        "category":  "kitchen",
        "rating":  3.9,
        "price":  358,
        "reviews":  49888,
        "affiliate_link":  "https://www.amazon.com/dp/B0064380017?tag=vh0805-20",
        "image":  "https://images.unsplash.com/photo-1556909114-f6e7ad7d3136?w=800",
        "date":  "2026-02-27"
    },
    {
        "asin":  "B0640523933",
        "title":  "USB Microphone Podcast 3",
        "slug":  "usb-microphone-podcast-285",
        "category":  "electronics",
        "rating":  4,
        "price":  359,
        "reviews":  49889,
        "affiliate_link":  "https://www.amazon.com/dp/B0640523933?tag=vh0805-20",
        "image":  "https://images.unsplash.com/photo-1498049794561-7780e7231661?w=800",
        "date":  "2026-02-27"
    },
    {
        "asin":  "B0526335717",
        "title":  "Car Audio System 3",
        "slug":  "car-audio-system-286",
        "category":  "audio",
        "rating":  4,
        "price":  360,
        "reviews":  49890,
        "affiliate_link":  "https://www.amazon.com/dp/B0526335717?tag=vh0805-20",
        "image":  "https://images.unsplash.com/photo-1505740420928-5e560c06d30e?w=800",
        "date":  "2026-02-27"
    },
    {
        "asin":  "B0731816131",
        "title":  "Business Smart Watch 3",
        "slug":  "business-smart-watch-287",
        "category":  "smartwatches",
        "rating":  4.1,
        "price":  361,
        "reviews":  49891,
        "affiliate_link":  "https://www.amazon.com/dp/B0731816131?tag=vh0805-20",
        "image":  "https://images.unsplash.com/photo-1523275335684-37898b6baf30?w=800",
        "date":  "2026-02-27"
    },
    {
        "asin":  "B0855333692",
        "title":  "Capture Card 4K 3",
        "slug":  "capture-card-4k-288",
        "category":  "gaming",
        "rating":  4.1,
        "price":  362,
        "reviews":  49892,
        "affiliate_link":  "https://www.amazon.com/dp/B0855333692?tag=vh0805-20",
        "image":  "https://images.unsplash.com/photo-1606144042614-b2417e99c4e3?w=800",
        "date":  "2026-02-27"
    },
    {
        "asin":  "B0199827952",
        "title":  "Window Cleaner Robot 3",
        "slug":  "window-cleaner-robot-289",
        "category":  "home",
        "rating":  4.2,
        "price":  363,
        "reviews":  49893,
        "affiliate_link":  "https://www.amazon.com/dp/B0199827952?tag=vh0805-20",
        "image":  "https://images.unsplash.com/photo-1556909114-fcd25c85cd64?w=800",
        "date":  "2026-02-27"
    },
    {
        "asin":  "B0079000390",
        "title":  "Jump Rope Speed 3",
        "slug":  "jump-rope-speed-290",
        "category":  "fitness",
        "rating":  3.8,
        "price":  385,
        "reviews":  49915,
        "affiliate_link":  "https://www.amazon.com/dp/B0079000390?tag=vh0805-20",
        "image":  "https://images.unsplash.com/photo-1571019614242-c5c5dee9f50b?w=800",
        "date":  "2026-02-27"
    },
    {
        "asin":  "B0928254480",
        "title":  "YouTube TV Box 3",
        "slug":  "youtube-tv-box-291",
        "category":  "streaming",
        "rating":  3.8,
        "price":  386,
        "reviews":  49916,
        "affiliate_link":  "https://www.amazon.com/dp/B0928254480?tag=vh0805-20",
        "image":  "https://images.unsplash.com/photo-1593359677879-a4bb92f829d1?w=800",
        "date":  "2026-02-27"
    },
    {
        "asin":  "B0009146989",
        "title":  "Window Sensor Alarm 3",
        "slug":  "window-sensor-alarm-292",
        "category":  "smart-home",
        "rating":  3.9,
        "price":  387,
        "reviews":  49917,
        "affiliate_link":  "https://www.amazon.com/dp/B0009146989?tag=vh0805-20",
        "image":  "https://images.unsplash.com/photo-1558089687-f282ffcbc126?w=800",
        "date":  "2026-02-27"
    },
    {
        "asin":  "B0783827800",
        "title":  "Case with Stand 3",
        "slug":  "case-with-stand-293",
        "category":  "kindle",
        "rating":  3.9,
        "price":  388,
        "reviews":  49918,
        "affiliate_link":  "https://www.amazon.com/dp/B0783827800?tag=vh0805-20",
        "image":  "https://images.unsplash.com/photo-1544716278-ca5e3f4abd8c?w=800",
        "date":  "2026-02-27"
    },
    {
        "asin":  "B0574712454",
        "title":  "Grill Basket Veggies 3",
        "slug":  "grill-basket-veggies-294",
        "category":  "grills",
        "rating":  4,
        "price":  389,
        "reviews":  49919,
        "affiliate_link":  "https://www.amazon.com/dp/B0574712454?tag=vh0805-20",
        "image":  "https://images.unsplash.com/photo-1529193591184-b1d58069ecdd?w=800",
        "date":  "2026-02-27"
    },
    {
        "asin":  "B0516649085",
        "title":  "Pizza Oven Countertop 3",
        "slug":  "pizza-oven-countertop-295",
        "category":  "kitchen",
        "rating":  4,
        "price":  390,
        "reviews":  49920,
        "affiliate_link":  "https://www.amazon.com/dp/B0516649085?tag=vh0805-20",
        "image":  "https://images.unsplash.com/photo-1556909114-f6e7ad7d3136?w=800",
        "date":  "2026-02-27"
    },
    {
        "asin":  "B0421944985",
        "title":  "Ring Light 12\" 3",
        "slug":  "ring-light-12-296",
        "category":  "electronics",
        "rating":  4.1,
        "price":  391,
        "reviews":  49921,
        "affiliate_link":  "https://www.amazon.com/dp/B0421944985?tag=vh0805-20",
        "image":  "https://images.unsplash.com/photo-1498049794561-7780e7231661?w=800",
        "date":  "2026-02-27"
    },
    {
        "asin":  "B0549140801",
        "title":  "Home Theater System 3",
        "slug":  "home-theater-system-297",
        "category":  "audio",
        "rating":  4.1,
        "price":  392,
        "reviews":  49922,
        "affiliate_link":  "https://www.amazon.com/dp/B0549140801?tag=vh0805-20",
        "image":  "https://images.unsplash.com/photo-1505740420928-5e560c06d30e?w=800",
        "date":  "2026-02-27"
    },
    {
        "asin":  "B0260220190",
        "title":  "Kids GPS Watch Phone 3",
        "slug":  "kids-gps-watch-phone-298",
        "category":  "smartwatches",
        "rating":  4.2,
        "price":  393,
        "reviews":  49923,
        "affiliate_link":  "https://www.amazon.com/dp/B0260220190?tag=vh0805-20",
        "image":  "https://images.unsplash.com/photo-1523275335684-37898b6baf30?w=800",
        "date":  "2026-02-27"
    },
    {
        "asin":  "B0446763316",
        "title":  "Streaming Microphone USB 3",
        "slug":  "streaming-microphone-usb-299",
        "category":  "gaming",
        "rating":  4.2,
        "price":  394,
        "reviews":  49924,
        "affiliate_link":  "https://www.amazon.com/dp/B0446763316?tag=vh0805-20",
        "image":  "https://images.unsplash.com/photo-1606144042614-b2417e99c4e3?w=800",
        "date":  "2026-02-27"
    }
]
